setup.py
yhlogin/__init__.py
yhlogin/yhlogin.py
yhlogin-1.0.13.dist-info/licenses/LICENSE
yhlogin-1.0.13.dist-info/METADATA
yhlogin-1.0.13.dist-info/WHEEL
yhlogin-1.0.13.dist-info/top_level.txt
yhlogin-1.0.13.dist-info/RECORD
