Metadata-Version: 2.4
Name: yhlogin
Version: 1.0.13
Summary: YH统一登录认证API
Author-email: zhang3 <675942084@qq.com>
Classifier: Programming Language :: Python :: 3
Classifier: License :: OSI Approved :: MIT License
Classifier: Operating System :: OS Independent
Requires-Python: >=3.8
License-File: LICENSE
Requires-Dist: httpx>=0.24.0
Requires-Dist: pyotp>=2.8.0
Requires-Dist: tenacity>=8.2.0
Dynamic: license-file
